MANIFEST.in
setup.py
django_foundation_icons.egg-info/PKG-INFO
django_foundation_icons.egg-info/SOURCES.txt
django_foundation_icons.egg-info/dependency_links.txt
django_foundation_icons.egg-info/top_level.txt
foundation_icons/__init__.py
foundation_icons/models.py
foundation_icons/static/foundation-icons.css
foundation_icons/static/foundation-icons.eot
foundation_icons/static/foundation-icons.scss
foundation_icons/static/foundation-icons.svg
foundation_icons/static/foundation-icons.ttf
foundation_icons/static/foundation-icons.woff
foundation_icons/static/svgs/fi-address-book.svg
foundation_icons/static/svgs/fi-alert.svg
foundation_icons/static/svgs/fi-align-center.svg
foundation_icons/static/svgs/fi-align-justify.svg
foundation_icons/static/svgs/fi-align-left.svg
foundation_icons/static/svgs/fi-align-right.svg
foundation_icons/static/svgs/fi-anchor.svg
foundation_icons/static/svgs/fi-annotate.svg
foundation_icons/static/svgs/fi-archive.svg
foundation_icons/static/svgs/fi-arrow-down.svg
foundation_icons/static/svgs/fi-arrow-left.svg
foundation_icons/static/svgs/fi-arrow-right.svg
foundation_icons/static/svgs/fi-arrow-up.svg
foundation_icons/static/svgs/fi-arrows-compress.svg
foundation_icons/static/svgs/fi-arrows-expand.svg
foundation_icons/static/svgs/fi-arrows-in.svg
foundation_icons/static/svgs/fi-arrows-out.svg
foundation_icons/static/svgs/fi-asl.svg
foundation_icons/static/svgs/fi-asterisk.svg
foundation_icons/static/svgs/fi-at-sign.svg
foundation_icons/static/svgs/fi-background-color.svg
foundation_icons/static/svgs/fi-battery-empty.svg
foundation_icons/static/svgs/fi-battery-full.svg
foundation_icons/static/svgs/fi-battery-half.svg
foundation_icons/static/svgs/fi-bitcoin-circle.svg
foundation_icons/static/svgs/fi-bitcoin.svg
foundation_icons/static/svgs/fi-blind.svg
foundation_icons/static/svgs/fi-bluetooth.svg
foundation_icons/static/svgs/fi-bold.svg
foundation_icons/static/svgs/fi-book-bookmark.svg
foundation_icons/static/svgs/fi-book.svg
foundation_icons/static/svgs/fi-bookmark.svg
foundation_icons/static/svgs/fi-braille.svg
foundation_icons/static/svgs/fi-burst-new.svg
foundation_icons/static/svgs/fi-burst-sale.svg
