Metadata-Version: 1.1
Name: django-foundation-icons
Version: 3.1
Summary: Zurb Foundation Icons (http://zurb.com/playground/foundation-icon-fonts-3) static files packaged in a Django app.
Home-page: https://github.com/benbacardi/django-foundation-icons
Author: Ben Cardy
Author-email: benbacardi@gmail.com
License: MIT
Keywords: django,zurb,foundation,staticfiles,icons
Platform: any
Classifier: Development Status :: 5 - Production/Stable
Classifier: Environment :: Web Environment
Classifier: Framework :: Django
Classifier: Intended Audience :: Developers
Classifier: Natural Language :: English
Classifier: License :: OSI Approved :: MIT License
Classifier: Operating System :: OS Independent
Classifier: Programming Language :: Python
Classifier: Topic :: Utilities
